LICENSE
README.md
pyproject.toml
setup.cfg
setup.py
divvy/__init__.py
divvy/divvy_request.py
divvy/live.py
divvy/pricing.py
divvy/stations.py
divvy/geo/__init__.py
divvy/geo/fees.geojson
divvy/historical/__init__.py
divvy/historical/dates.py
divvy/historical/historical.py
python_divvy.egg-info/PKG-INFO
python_divvy.egg-info/SOURCES.txt
python_divvy.egg-info/dependency_links.txt
python_divvy.egg-info/requires.txt
python_divvy.egg-info/top_level.txt