Metadata-Version: 2.1
Name: python-divvy
Version: 0.0.5
Summary: Python Client for Chicago Ridesharing Data.
Home-page: https://github.com/wd60622/divvy
Author: William Dean
Author-email: wd60622@gmail.com
License: MIT
Classifier: License :: OSI Approved :: MIT License
Classifier: Programming Language :: Python :: 3
Classifier: Programming Language :: Python :: 3.7
Classifier: Programming Language :: Python :: 3.8
Classifier: Programming Language :: Python :: 3.9
Classifier: Programming Language :: Python :: 3.10
Provides-Extra: test
License-File: LICENSE
